[
  {
    "bolumAdi": "Bilgisayar",
    "fakulteAdi": "Elektrik-Elektronik Fakültesi",
    "url": ""
  },
  {
    "bolumAdi": "Biyomedikal",
    "fakulteAdi": "Elektrik-Elektronik Fakültesi",
    "url": ""
  },
  {
    "bolumAdi": "Elektrik",
    "fakulteAdi": "Elektrik-Elektronik Fakültesi",
    "url": ""
  },
  {
    "bolumAdi": "Elektronik ve Haberleşme",
    "fakulteAdi": "Elektrik-Elektronik Fakültesi",
    "url": ""
  },
  {
    "bolumAdi": "Kontrol ve Otomasyon",
    "fakulteAdi": "Elektrik-Elektronik Fakültesi",
    "url": ""
  },
  {
    "bolumAdi": "Zeka ve Veri",
    "fakulteAdi": "Elektrik-Elektronik Fakültesi",
    "url": ""
  },
  {
    "bolumAdi": "Makineleri",
    "fakulteAdi": "Gemi İnşaatı ve Denizcilik Fakültesi",
    "url": ""
  },
  {
    "bolumAdi": "İşletme",
    "fakulteAdi": "Gemi İnşaatı ve Denizcilik Fakültesi",
    "url": ""
  },
  {
    "bolumAdi": "İnşaat",
    "fakulteAdi": "İnşaat Fakültesi",
    "url": ""
  },
  {
    "bolumAdi": "Çevre",
    "fakulteAdi": "İnşaat Fakültesi",
    "url": ""
  },
  {
    "bolumAdi": "Harita",
    "fakulteAdi": "İnşaat Fakültesi",
    "url": ""
  },
  {
    "bolumAdi": "Biyomühendislik",
    "fakulteAdi": "Kimya-Metalurji Fakültesi",
    "url": ""
  },
  {
    "bolumAdi": "Gıda",
    "fakulteAdi": "Kimya-Metalurji Fakültesi",
    "url": ""
  },
  {
    "bolumAdi": "Kimya",
    "fakulteAdi": "Kimya-Metalurji Fakültesi",
    "url": ""
  },
  {
    "bolumAdi": "Matematik",
    "fakulteAdi": "Kimya-Metalurji Fakültesi",
    "url": ""
  },
  {
    "bolumAdi": "Metalurji ve Malzeme",
    "fakulteAdi": "Kimya-Metalurji Fakültesi",
    "url": ""
  },
  {
    "bolumAdi": "Makine",
    "fakulteAdi": "Makine Fakültesi",
    "url": ""
  },
  {
    "bolumAdi": "Endüstri",
    "fakulteAdi": "Makine Fakültesi",
    "url": ""
  },
  {
    "bolumAdi": "Mekatronik",
    "fakulteAdi": "Makine Fakültesi",
    "url": ""
  },
  {
    "bolumAdi": "Mimarlık",
    "fakulteAdi": "Mimarlık Fakültesi",
    "url": ""
  },
  {
    "bolumAdi": "Planlama",
    "fakulteAdi": "Mimarlık Fakültesi",
    "url": ""
  },
  {
    "bolumAdi": "Koruma ve Onarım",
    "fakulteAdi": "Mimarlık Fakültesi",
    "url": ""
  },
  {
    "bolumAdi": "Sanatları",
    "fakulteAdi": "Sanat ve Tasarım Fakültesi",
    "url": ""
  },
  {
    "bolumAdi": "İletişim ve Tasarımı",
    "fakulteAdi": "Sanat ve Tasarım Fakültesi",
    "url": ""
  },
  {
    "bolumAdi": "Sanat",
    "fakulteAdi": "Sanat ve Tasarım Fakültesi",
    "url": ""
  }
]